mygeniuspackage/__init__.py
mygeniuspackage/show_data.py
mygeniuspackage-0.2.dist-info/METADATA
mygeniuspackage-0.2.dist-info/WHEEL
mygeniuspackage-0.2.dist-info/top_level.txt
mygeniuspackage-0.2.dist-info/RECORD
